{
   "type" : "root",
   "children" : [
      {
         "type" : "sequence",
         "children" : [
            {
               "type" : "leaf",
               "children" : [
                  
               ],
               "name" : "",
               "command" : {
                  "type" : "leave_battle"
               },
               "_editor" : {
                  "position" : [
                     -636.6667,
                     300.6667
                  ]
               }
            },
            {
               "type" : "leaf",
               "children" : [
                  
               ],
               "name" : "3p",
               "command" : {
                  "type" : "set_random_point_of_interest",
                  "point_of_interest" : "patrol",
                  "radius" : 4,
                  "near_with_point_of_interest" : false,
                  "target_near_point_of_interest" : ""
               },
               "_editor" : {
                  "position" : [
                     -314.6667,
                     300.6667
                  ]
               }
            },
            {
               "type" : "leaf",
               "children" : [
                  
               ],
               "name" : "4p",
               "command" : {
                  "type" : "has_point_of_interest",
                  "point_of_interest" : "patrol"
               },
               "_editor" : {
                  "position" : [
                     96.66666,
                     350
                  ]
               }
            },
            {
               "type" : "leaf",
               "children" : [
                  
               ],
               "name" : "5p",
               "command" : {
                  "type" : "move_to_point_of_interest",
                  "point_of_interest" : "patrol"
               },
               "_editor" : {
                  "position" : [
                     504,
                     350
                  ]
               }
            }
         ],
         "name" : "2p",
         "_editor" : {
            "position" : [
               22.66667,
               175.3333
            ]
         }
      }
   ],
   "name" : "1p",
   "_editor" : {
      "position" : [
         0,
         0
      ]
   }
}